implies-0.4.5.dist-info/METADATA
implies-0.4.5.dist-info/WHEEL
implies/__init__.py
implies/implies.cpython-39-darwin.so
implies-0.4.5.dist-info/RECORD
