Metadata-Version: 2.1
Name: implies
Version: 0.4.5
Summary: A parser for logical formulas
Keywords: logic,binary_tree,tree,graph
License: MIT
Project-URL: Source Code, https://github.com/armaan-rashid/implies
